llama_index/tools/multion/__init__.py
llama_index/tools/multion/base.py
llama_index_tools_multion-0.5.1.dist-info/METADATA
llama_index_tools_multion-0.5.1.dist-info/WHEEL
llama_index_tools_multion-0.5.1.dist-info/licenses/LICENSE
llama_index_tools_multion-0.5.1.dist-info/RECORD
