Metadata-Version: 2.4
Name: llama-index-tools-multion
Version: 0.5.1
Summary: llama-index tools multion integration
Author-email: Your Name <you@example.com>
Maintainer: ajhofmann
License-Expression: MIT
License-File: LICENSE
Requires-Python: <4.0,>=3.9
Requires-Dist: llama-index-core<0.15,>=0.13.0
Requires-Dist: multion<0.4,>=0.3.11
Requires-Dist: pillow<11,>=10.2.0
Requires-Dist: pytesseract<0.4,>=0.3.10
